Zuoxiangqicheng/README.md
Zuoxiangqicheng/__init__.py
Zuoxiangqicheng/__main__.py
Zuoxiangqicheng/file.epub
Zuoxiangqicheng/index.html
Zuoxiangqicheng/css/__init__.py
Zuoxiangqicheng/css/annotations.css
Zuoxiangqicheng/css/main.css
Zuoxiangqicheng/css/normalize.css
Zuoxiangqicheng/css/popup.css
Zuoxiangqicheng/font/__init__.py
Zuoxiangqicheng/font/fontello.eot
Zuoxiangqicheng/font/fontello.svg
Zuoxiangqicheng/font/fontello.ttf
Zuoxiangqicheng/font/fontello.woff
Zuoxiangqicheng/img/__init__.py
Zuoxiangqicheng/img/annotator-glyph-sprite.png
Zuoxiangqicheng/img/annotator-icon-sprite.png
Zuoxiangqicheng/img/apple-touch-icon.png
Zuoxiangqicheng/img/cancelfullscreen.png
Zuoxiangqicheng/img/close.png
Zuoxiangqicheng/img/fullscreen.png
Zuoxiangqicheng/img/loader.gif
Zuoxiangqicheng/img/menu-icon.png
Zuoxiangqicheng/img/save.png
Zuoxiangqicheng/img/saved.png
Zuoxiangqicheng/img/settings-s.png
Zuoxiangqicheng/img/settings.png
Zuoxiangqicheng/img/star.png
Zuoxiangqicheng/js/__init__.py
Zuoxiangqicheng/js/epub.js
Zuoxiangqicheng/js/epub.min.js
Zuoxiangqicheng/js/epub.min.map
Zuoxiangqicheng/js/hooks.min.js
Zuoxiangqicheng/js/hooks.min.map
Zuoxiangqicheng/js/reader.js
Zuoxiangqicheng/js/reader.js.map
Zuoxiangqicheng/js/reader.min.js
Zuoxiangqicheng/js/reader.min.map
Zuoxiangqicheng/js/hooks/__init__.py
Zuoxiangqicheng/js/hooks/extensions/__init__.py
Zuoxiangqicheng/js/hooks/extensions/highlight.js
Zuoxiangqicheng/js/libs/__init__.py
Zuoxiangqicheng/js/libs/jquery.min.js
Zuoxiangqicheng/js/libs/localforage.min.js
Zuoxiangqicheng/js/libs/screenfull.js
Zuoxiangqicheng/js/libs/screenfull.min.js
Zuoxiangqicheng/js/libs/zip.min.js
Zuoxiangqicheng/js/plugins/__init__.py
Zuoxiangqicheng/js/plugins/hypothesis.js
Zuoxiangqicheng/js/plugins/search.js
zuoxiangqicheng-2024.3.5.0.dist-info/METADATA
zuoxiangqicheng-2024.3.5.0.dist-info/WHEEL
zuoxiangqicheng-2024.3.5.0.dist-info/entry_points.txt
zuoxiangqicheng-2024.3.5.0.dist-info/top_level.txt
zuoxiangqicheng-2024.3.5.0.dist-info/RECORD
